odoo/addons/cross_connect_client/README.rst
odoo/addons/cross_connect_client/__init__.py
odoo/addons/cross_connect_client/__manifest__.py
odoo/addons/cross_connect_client/controllers/__init__.py
odoo/addons/cross_connect_client/controllers/cross_connect.py
odoo/addons/cross_connect_client/i18n/cross_connect_client.pot
odoo/addons/cross_connect_client/i18n/it.po
odoo/addons/cross_connect_client/models/__init__.py
odoo/addons/cross_connect_client/models/cross_connect_server.py
odoo/addons/cross_connect_client/models/res_groups.py
odoo/addons/cross_connect_client/readme/CONTRIBUTORS.md
odoo/addons/cross_connect_client/readme/DESCRIPTION.md
odoo/addons/cross_connect_client/readme/USAGE.md
odoo/addons/cross_connect_client/security/ir_model_access.xml
odoo/addons/cross_connect_client/static/description/icon.png
odoo/addons/cross_connect_client/static/description/index.html
odoo/addons/cross_connect_client/static/description/web_icon_data.png
odoo/addons/cross_connect_client/tests/__init__.py
odoo/addons/cross_connect_client/tests/test_cross_connect_client.py
odoo/addons/cross_connect_client/views/cross_connect_server_views.xml
odoo_addon_cross_connect_client-16.0.1.0.0.10.dist-info/METADATA
odoo_addon_cross_connect_client-16.0.1.0.0.10.dist-info/WHEEL
odoo_addon_cross_connect_client-16.0.1.0.0.10.dist-info/top_level.txt
odoo_addon_cross_connect_client-16.0.1.0.0.10.dist-info/RECORD
